Workbook

Sheet Inputs
A1: Unit Economics Model — Marketing Channel Inputs
A3: Parameter | B3: Google Ads | C3: Facebook Ads | D3: SEO | E3: Email | G3: Notes
A4: Monthly Budget ($) | B4: 8000 | C4: 6000 | D4: 2000 | E4: 500 | G4: Monthly marketing spend allocated to channel
A5: New Customers / Month | B5: 137 | C5: 86 | D5: 162 | E5: 53 | G5: Average monthly customer acquisitions
A6: CAC ($) | B6: 78.8 | C6: 88.9 | D6: 14.9 | E6: 10.7 | G6: Cost per Acquired Customer = Spend / New Customers
A7: Avg Monthly ARPU ($) | B7: 48 | C7: 39 | D7: 55 | E7: 43 | G7: Average Revenue per User per Month
A8: Gross Margin (%) | B8: 0.72 | C8: 0.7 | D8: 0.76 | E8: 0.74 | G8: Revenue remaining after COGS
A9: Monthly Churn Rate (%) | B9: 0.055 | C9: 0.082 | D9: 0.038 | E9: 0.028 | G9: % of customers lost per month
A10: LTV ($) | B10: =C5*C6/C7 | C10: =D5*D6/D7 | D10: =E5*E6/E7 | E10: =F5*F6/F7 | G10: LTV = ARPU × Margin / Monthly Churn
A11: LTV / CAC Ratio | B11: =C8/C4 | C11: =D8/D4 | D11: =E8/E4 | E11: =F8/F4 | G11: Healthy: > 3x. Ideal: > 5x
A12: Payback Period (months) | B12: =C4/(C5*C6) | C12: =D4/(D5*D6) | D12: =E4/(E5*E6) | E12: =F4/(F5*F6) | G12: Months to recover CAC
A13: 12-Month Gross Profit ($) | B13: =C5*12*C5*C6*(1-(1-C7)^12)/C7 | C13: =D5*12*D5*D6*(1-(1-D7)^12)/D7 | D13: =E5*12*E5*E6*(1-(1-E7)^12)/E7 | E13: =F5*12*F5*F6*(1-(1-F7)^12)/F7 | G13: Gross profit per cohort over 12 months

Sheet Unit Economics
A1: Unit Economics Summary — All Channels
A3: Metric | B3: Google Ads | C3: Facebook Ads | D3: SEO | E3: Email | F3: Total / Avg
A4: Monthly Budget ($) | B4: =Inputs!B4 | C4: =Inputs!C4 | D4: =Inputs!D4 | E4: =Inputs!E4 | F4: =SUM(B4:E4)
A5: New Customers / Month | B5: =Inputs!B5 | C5: =Inputs!C5 | D5: =Inputs!D5 | E5: =Inputs!E5 | F5: =SUM(B5:E5)
A6: CAC ($) | B6: =Inputs!B6 | C6: =Inputs!C6 | D6: =Inputs!D6 | E6: =Inputs!E6 | F6: =SUMPRODUCT(B4:E4,B6:E6)/SUM(B4:E4)
A7: LTV ($) | B7: =Inputs!B8 | C7: =Inputs!C8 | D7: =Inputs!D8 | E7: =Inputs!E8 | F7: =SUMPRODUCT(B5:E5,B8:E8)/SUM(B5:E5)
A8: LTV / CAC | B8: =Inputs!B9 | C8: =Inputs!C9 | D8: =Inputs!D9 | E8: =Inputs!E9 | F8: =F8/F6
A9: Payback Period (months) | B9: =Inputs!B10 | C9: =Inputs!C10 | D9: =Inputs!D10 | E9: =Inputs!E10 | F9: =SUMPRODUCT(B5:E5,B10:E10)/SUM(B5:E5)
A10: Monthly Gross Profit ($) | B10: =B5*Inputs!B5*Inputs!B6 | C10: =C5*Inputs!C5*Inputs!C6 | D10: =D5*Inputs!D5*Inputs!D6 | E10: =E5*Inputs!E5*Inputs!E6 | F10: =SUM(B11:E11)
A11: Budget Share (%) | B11: =B4/F4 | C11: =C4/F4 | D11: =D4/F4 | E11: =E4/F4 | F11: =SUM(B12:E12)
A12: Revenue Share (%) | B12: =B5*Inputs!B5/SUM(B5:E5*Inputs!B5:Inputs!E5) | C12: =C5*Inputs!C5/SUM(B5:E5*Inputs!B5:Inputs!E5) | D12: =D5*Inputs!D5/SUM(B5:E5*Inputs!B5:Inputs!E5) | E12: =E5*Inputs!E5/SUM(B5:E5*Inputs!B5:Inputs!E5) | F12: =SUM(B13:E13)

Sheet Scenarios
A1: Budget Reallocation Scenarios — Total $16 500 / Month
A3: Channel / Metric | B3: Current | C3: Optimised | D3: Aggressive SEO
A4: BUDGET ALLOCATION
A5: Google Ads ($) | B5: 8000 | C5: 7000 | D5: 6000
A6: Facebook Ads ($) | B6: 6000 | C6: 3500 | D6: 2000
A7: SEO ($) | B7: 2000 | C7: 5000 | D7: 7500
A8: Email ($) | B8: 500 | C8: 1000 | D8: 1000
A9: Total ($) | B9: 16500 | C9: 16500 | D9: 16500
A11: PROJECTED OUTCOMES
A12: New Customers / Mo | B12: 436 | C12: 490 | D12: 560
A13: Blended CAC ($) | B13: 37.8 | C13: 33.7 | D13: 29.5
A14: Blended LTV ($) | B14: 616 | C14: 720 | D14: 820
A15: LTV/CAC Ratio | B15: 16.3 | C15: 21.4 | D15: 27.8
A16: Monthly Gross Profit ($) | B16: 9700 | C16: 11200 | D16: 13100
A17: 12-Month incremental ($) | C17: 18000 | D17: 40800
